abis/__init__.py
abis/candlegenie.py
abis/dogebets.py
abis/pancakeswap.py
predictionbets/__init__.py
predictionbets/predictions.py
predictionbets/schemas.py
predictionbets/test_predictions.py
test_predictionbets/__init__.py
PredictionsWrapper-0.0.1.dist-info/METADATA
PredictionsWrapper-0.0.1.dist-info/WHEEL
PredictionsWrapper-0.0.1.dist-info/top_level.txt
PredictionsWrapper-0.0.1.dist-info/RECORD
