Metadata-Version: 2.1
Name: PredictionsWrapper
Version: 0.0.1
Summary: Wrapper for Popular Prediction Platforms
Home-page: https://github.com/DaryKeruita/predictionswrapper
Author: Dary Keruita
Author-email: <darykeruita@gmail.com>
License: UNKNOWN
Keywords: pancakeswap,prediction,predictions,pancakeswap prediction,dogebet,dogebets,candle genie,candle genie prediction,dogebets prediction,winning predictions,winning pancakeswap,dogebets winner
Platform: UNKNOWN
Classifier: Development Status :: 1 - Planning
Classifier: Intended Audience :: Developers
Classifier: Programming Language :: Python :: 3
Classifier: Operating System :: OS Independent
Requires-Python: >=3.8
Requires-Dist: pydantic
Requires-Dist: web3
